[ {"title": "Home",
    "pages": [
      {"title": "Introduction",
        "file": "introduction"},
      {"title": "Design Values",
        "file": "designValues",
        "url": "/DesignValues/embed.html"},
      {"title": "Add-ons",
        "file": "addons"}
      ]},
  {"title": "Visual Design",
    "pages": [
      {"title": "Colours",
        "file": "colours"},
      {"title": "Typography",
        "file": "typography"}
      ]},
  {"title": "Components",
    "pages": [
      {"title": "Controls",
        "file": "controls"},
      {"title": "Inputs",
        "file": "inputs"},
      {"title": "Glyphs",
        "file": "glyphs"},
      {"title": "Shapes",
        "file": "shapes"},
      {"title": "Panels",
        "file": "panels"}
      ]},
  {"title": "Resources",
    "pages": [
      {"title": "Downloads",
        "file": "downloads"}
      ]}
]
